odainipkg/__init__.py
odainipkg/odainipkg.py
odainipkg-0.1.0.dist-info/LICENSE
odainipkg-0.1.0.dist-info/WHEEL
odainipkg-0.1.0.dist-info/METADATA
odainipkg-0.1.0.dist-info/RECORD
